django_omnitenant/__init__.py
django_omnitenant/admin.py
django_omnitenant/apps.py
django_omnitenant/bootstrap.py
django_omnitenant/conf.py
django_omnitenant/constants.py
django_omnitenant/exceptions.py
django_omnitenant/middleware.py
django_omnitenant/models.py
django_omnitenant/routers.py
django_omnitenant/signals.py
django_omnitenant/tenant_context.py
django_omnitenant/utils.py
django_omnitenant/validators.py
django_omnitenant/views.py
django_omnitenant/backends/__init__.py
django_omnitenant/backends/base.py
django_omnitenant/backends/cache_backend.py
django_omnitenant/backends/database_backend.py
django_omnitenant/backends/schema_backend.py
django_omnitenant/backends/postgresql/__init__.py
django_omnitenant/backends/postgresql/base.py
django_omnitenant/management/commands/createtenant.py
django_omnitenant/management/commands/createtenantsuperuser.py
django_omnitenant/management/commands/migratealltenants.py
django_omnitenant/management/commands/migratetenant.py
django_omnitenant/management/commands/shell.py
django_omnitenant/migrations/__init__.py
django_omnitenant/patches/cache.py
django_omnitenant/patches/celery.py
django_omnitenant/resolvers/__init__.py
django_omnitenant/resolvers/base.py
django_omnitenant/resolvers/customdomain_resolver.py
django_omnitenant/resolvers/subdomain_resolver.py
django_omnitenant/tests/__init__.py
django_omnitenant/tests/testcases.py
django_omnitenant-0.2.0.dist-info/LICENSE
django_omnitenant-0.2.0.dist-info/METADATA
django_omnitenant-0.2.0.dist-info/WHEEL
django_omnitenant-0.2.0.dist-info/top_level.txt
django_omnitenant-0.2.0.dist-info/RECORD
