Metadata-Version: 2.2
Name: django-omnitenant
Version: 0.2.0
Summary: A Django app to allow multi-tenancy.
Author-email: Krishna Rimal <krishna.rimal@ajnalab.com>
License: BSD-3-Clause
Project-URL: Homepage, https://github.com/RahulRimal/django-omnitenant
Classifier: Environment :: Web Environment
Classifier: Framework :: Django
Classifier: Framework :: Django :: 5.2
Classifier: Intended Audience :: Developers
Classifier: Operating System :: OS Independent
Classifier: Programming Language :: Python
Classifier: Programming Language :: Python :: 3
Classifier: Programming Language :: Python :: 3 :: Only
Classifier: Programming Language :: Python :: 3.10
Classifier: Programming Language :: Python :: 3.11
Classifier: Programming Language :: Python :: 3.12
Classifier: Programming Language :: Python :: 3.13
Classifier: Topic :: Internet :: WWW/HTTP
Classifier: Topic :: Internet :: WWW/HTTP :: Dynamic Content
Requires-Python: >=3.10
License-File: LICENSE
Requires-Dist: django>=5.2
